cmd_clever-0.1.0.dist-info/licenses/LICENSE
cmdclever/__init__.py
cmdclever/__main__.py
cmdclever/agent.py
cmdclever/cli/__init__.py
cmdclever/cli/main.py
tests/__init__.py
tests/test_agent.py
tests/test_cli.py
cmd_clever-0.1.0.dist-info/METADATA
cmd_clever-0.1.0.dist-info/WHEEL
cmd_clever-0.1.0.dist-info/entry_points.txt
cmd_clever-0.1.0.dist-info/top_level.txt
cmd_clever-0.1.0.dist-info/RECORD
